Workbook

Sheet Assumptions
B2: ASSUMPTIONS
B4: Entry EBITDA ($M) | C4: 100
B5: Entry EV / EBITDA (x) | C5: 10
B6: Entry EV ($M) | C6: =C4*C5
B8: Leverage (Debt / EBITDA x) | C8: 5
B9: Entry Debt ($M) | C9: =C8*C4
B10: Interest rate (%) | C10: 0.08
B12: Transaction fees (% of EV) | C12: 0.02
B14: Revenue yr0 ($M) | C14: 250
B15: Revenue growth (%) | C15: 0.06
B16: EBITDA margin (%) | C16: 0.4
B17: D&A (% of revenue) | C17: 0.05
B18: Capex (% of revenue) | C18: 0.05
B19: Tax rate (%) | C19: 0.25
B21: Hold period (yrs) | C21: 5
B22: Exit EV / EBITDA (x) | C22: 10

Sheet Sources & Uses
B2: SOURCES & USES
B4: Uses
B5: Purchase Enterprise Value | C5: =Assumptions!C6
B6: Transaction fees | C6: =Assumptions!C12*Assumptions!C6
B7: Total Uses | C7: =SUM(C5:C6)
B9: Sources
B10: Debt | C10: =Assumptions!C9
B11: Sponsor Equity (plug) | C11: =C7-C10
B12: Total Sources | C12: =SUM(C10:C11)
B14: Check (Sources - Uses) | C14: =C12-C7

Sheet Operating Model
B2: OPERATING MODEL
B3: Year | C3: 1 | D3: 2 | E3: 3 | F3: 4 | G3: 5
B4: Revenue | C4: =Assumptions!C14*(1+Assumptions!C15) | D4: =C4*(1+Assumptions!C15) | E4: =D4*(1+Assumptions!C15) | F4: =E4*(1+Assumptions!C15) | G4: =F4*(1+Assumptions!C15)
B5: EBITDA | C5: =C4*Assumptions!C16 | D5: =D4*Assumptions!C16 | E5: =E4*Assumptions!C16 | F5: =F4*Assumptions!C16 | G5: =G4*Assumptions!C16
B6: D&A | C6: =C4*Assumptions!C17 | D6: =D4*Assumptions!C17 | E6: =E4*Assumptions!C17 | F6: =F4*Assumptions!C17 | G6: =G4*Assumptions!C17
B7: EBIT | C7: =C5-C6 | D7: =D5-D6 | E7: =E5-E6 | F7: =F5-F6 | G7: =G5-G6
B8: Capex | C8: =C4*Assumptions!C18 | D8: =D4*Assumptions!C18 | E8: =E4*Assumptions!C18 | F8: =F4*Assumptions!C18 | G8: =G4*Assumptions!C18
B9: Interest | C9: ='Debt Schedule'!C5 | D9: ='Debt Schedule'!D5 | E9: ='Debt Schedule'!E5 | F9: ='Debt Schedule'!F5 | G9: ='Debt Schedule'!G5
B10: EBT | C10: =C7-C9 | D10: =D7-D9 | E10: =E7-E9 | F10: =F7-F9 | G10: =G7-G9
B11: Tax | C11: =MAX(0,C10)*Assumptions!C19 | D11: =MAX(0,D10)*Assumptions!C19 | E11: =MAX(0,E10)*Assumptions!C19 | F11: =MAX(0,F10)*Assumptions!C19 | G11: =MAX(0,G10)*Assumptions!C19
B12: FCF (pre-sweep) | C12: =C5-C9-C11-C8 | D12: =D5-D9-D11-D8 | E12: =E5-E9-E11-E8 | F12: =F5-F9-F11-F8 | G12: =G5-G9-G11-G8

Sheet Debt Schedule
B2: DEBT SCHEDULE
B3: Year | C3: 1 | D3: 2 | E3: 3 | F3: 4 | G3: 5
B4: Beginning Debt | C4: ='Sources & Uses'!C10 | D4: =C7 | E4: =D7 | F4: =E7 | G4: =F7
B5: Interest | C5: =C4*Assumptions!C10 | D5: =D4*Assumptions!C10 | E5: =E4*Assumptions!C10 | F5: =F4*Assumptions!C10 | G5: =G4*Assumptions!C10
B6: FCF (cash sweep) | C6: ='Operating Model'!C12 | D6: ='Operating Model'!D12 | E6: ='Operating Model'!E12 | F6: ='Operating Model'!F12 | G6: ='Operating Model'!G12
B7: Ending Debt | C7: =MAX(0,C4-C6) | D7: =MAX(0,D4-D6) | E7: =MAX(0,E4-E6) | F7: =MAX(0,F4-F6) | G7: =MAX(0,G4-G6)

Sheet Returns
B2: RETURNS
B4: Exit EBITDA (yr5) | C4: ='Operating Model'!G5
B5: Exit EV / EBITDA (x) | C5: =Assumptions!C22
B6: Exit EV | C6: =C4*C5
B7: Net Debt at Exit | C7: ='Debt Schedule'!G7
B8: Exit Equity Value | C8: =C6-C7
B9: Entry Equity | C9: ='Sources & Uses'!C11
B10: MOIC | C10: =C8/C9
B11: Hold (yrs) | C11: =Assumptions!C21
B12: IRR | C12: =C10^(1/C11)-1

Sheet Checks
B2: CHECKS
B4: Sources = Uses | C4: =('Sources & Uses'!C14=0)
B5: Ending debt >= 0 (yr5) | C5: =('Debt Schedule'!G7>=0)
B6: MOIC > 0 | C6: =(Returns!C10>0)
B7: IRR is finite | C7: =ISNUMBER(Returns!C12)
